django_plans_payments-2.0.2.dist-info/licenses/AUTHORS.rst
django_plans_payments-2.0.2.dist-info/licenses/LICENSE
plans_payments/__init__.py
plans_payments/admin.py
plans_payments/apps.py
plans_payments/models.py
plans_payments/urls.py
plans_payments/views.py
plans_payments/migrations/0001_initial.py
plans_payments/migrations/0002_payment_transaction_fee.py
plans_payments/migrations/0003_auto_20201006_0855.py
plans_payments/migrations/0004_payment_billing_phone.py
plans_payments/migrations/0005_payment_plans_payme_status_9ad17d_idx_and_more.py
plans_payments/migrations/__init__.py
plans_payments/static/__init__.py
plans_payments/static/img/__init__.py
plans_payments/static/img/visa-logo.svg
plans_payments/templates/__init__.py
plans_payments/templates/mail/__init__.py
plans_payments/templates/plans/__init__.py
plans_payments/templates/plans/order_detail.html
plans_payments/templates/plans_payments/__init__.py
plans_payments/templates/plans_payments/failure.html
plans_payments/templates/plans_payments/payment.html
plans_payments/templates/plans_payments/payment_buttons.html
plans_payments/templates/plans_payments/success.html
plans_payments/templatetags/__init__.py
plans_payments/templatetags/payment_buttons.py
django_plans_payments-2.0.2.dist-info/METADATA
django_plans_payments-2.0.2.dist-info/WHEEL
django_plans_payments-2.0.2.dist-info/top_level.txt
django_plans_payments-2.0.2.dist-info/RECORD
