Metadata-Version: 2.4
Name: django-plans-payments
Version: 2.0.2
Summary: Integration between django-plans and django-payments.
Home-page: https://github.com/PetrDlouhy/django-plans-payments
Author: Petr Dlouhý
Author-email: petr.dlouhy@email.cz
License: MIT
Keywords: django-plans-payments
Classifier: Development Status :: 3 - Alpha
Classifier: Framework :: Django :: 3.2
Classifier: Framework :: Django :: 4.0
Classifier: Framework :: Django :: 4.1
Classifier: Framework :: Django :: 5.0
Classifier: Framework :: Django :: 5.1
Classifier: Intended Audience :: Developers
Classifier: Natural Language :: English
Classifier: Programming Language :: Python :: 3
Classifier: Programming Language :: Python :: 3.8
Classifier: Programming Language :: Python :: 3.9
Classifier: Programming Language :: Python :: 3.10
Classifier: Programming Language :: Python :: 3.11
Classifier: Programming Language :: Python :: 3.12
Classifier: Programming Language :: Python :: 3.13
License-File: LICENSE
License-File: AUTHORS.rst
Requires-Dist: django-payments
Requires-Dist: django-plans
Requires-Dist: django-related-admin
Dynamic: author
Dynamic: author-email
Dynamic: classifier
Dynamic: description
Dynamic: home-page
Dynamic: keywords
Dynamic: license
Dynamic: license-file
Dynamic: requires-dist
Dynamic: summary
